{"nodes": [{"id": "migration_sections_topic_sections", "label": "topic_sections table", "file_type": "concept", "source_file": "backend/scripts/migration_sections.sql", "source_location": "L5", "source_url": null, "captured_at": null, "author": null, "contributor": null}, {"id": "migration_sections_clips_section_index", "label": "clips.section_index column", "file_type": "concept", "source_file": "backend/scripts/migration_sections.sql", "source_location": "L17", "source_url": null, "captured_at": null, "author": null, "contributor": null}], "edges": [], "hyperedges": []}